flask_lambda.py
flask_lambda_python36_lb-0.6.0.dist-info/LICENSE
flask_lambda_python36_lb-0.6.0.dist-info/METADATA
flask_lambda_python36_lb-0.6.0.dist-info/WHEEL
flask_lambda_python36_lb-0.6.0.dist-info/top_level.txt
flask_lambda_python36_lb-0.6.0.dist-info/RECORD
